dcor_control/__init__.py
dcor_control/_version.py
dcor_control/backup.py
dcor_control/update.py
dcor_control/util.py
dcor_control/cli/__init__.py
dcor_control/cli/backup.py
dcor_control/cli/common.py
dcor_control/cli/develop.py
dcor_control/cli/inspect.py
dcor_control/cli/reset.py
dcor_control/cli/status.py
dcor_control/cli/update.py
dcor_control/inspect/__init__.py
dcor_control/inspect/common.py
dcor_control/inspect/config_ckan.py
dcor_control/resources/__init__.py
dcor_control/resources/compatible_versions.txt
dcor_control/resources/dcor_defaults.ini.template
dcor_control/resources/branding/testing/public/.gitignore
dcor_control/resources/branding/testing/public/favicon.ico
dcor_control/resources/branding/testing/public/favicon.svg
dcor_control/resources/branding/testing/public/images/dcor-076.png
dcor_control/resources/branding/testing/public/images/dcor-096.png
dcor_control/resources/branding/testing/public/images/dcor-152.png
dcor_control/resources/branding/testing/public/images/dcor-180.png
dcor_control/resources/site_dcor-docker/dcor_config.json
dcor_control-1.17.3.dist-info/licenses/LICENSE
dcor_control-1.17.3.dist-info/METADATA
dcor_control-1.17.3.dist-info/WHEEL
dcor_control-1.17.3.dist-info/entry_points.txt
dcor_control-1.17.3.dist-info/top_level.txt
dcor_control-1.17.3.dist-info/RECORD
