Metadata-Version: 2.4
Name: dcor_control
Version: 1.17.3
Summary: CLI for maintaining DCOR installations
Author: Paul Müller
Maintainer-email: Paul Müller <dev@craban.de>
License: GNU Affero General Public License v3 or later (AGPLv3+)
Project-URL: source, https://github.com/DCOR-dev/dcor_control
Project-URL: tracker, https://github.com/DCOR-dev/dcor_control/issues
Project-URL: changelog, https://github.com/DCOR-dev/dcor_control/blob/main/CHANGELOG
Keywords: DC,DCOR,deformability,cytometry
Classifier: Operating System :: OS Independent
Classifier: Programming Language :: Python :: 3
Classifier: Topic :: Scientific/Engineering :: Visualization
Classifier: Intended Audience :: Science/Research
Requires-Python: <4,>=3.8
License-File: LICENSE
Requires-Dist: appdirs
Requires-Dist: ckan<3,>=2.11.3
Requires-Dist: click>=7
Requires-Dist: cryptography>=41
Requires-Dist: ckanext-dc_log_view>=1.0.0
Requires-Dist: ckanext-dc_serve>=1.0.7
Requires-Dist: ckanext-dc_view>=1.0.1
Requires-Dist: ckanext-dcor_depot>=1.0.3
Requires-Dist: ckanext-dcor_schemas>=1.0.0
Requires-Dist: ckanext-dcor_theme>=1.1.2
Requires-Dist: dcor_shared>=1.0.4
Requires-Dist: importlib_resources
Requires-Dist: numpy>=1.21
Requires-Dist: uwsgi>=2.0.26
Dynamic: license-file
